bbdata/__init__.py
bbdata/config.py
bbdata/exceptions.py
bbdata/response.py
bbdata/util.py
bbdata/endpoint/__init__.py
bbdata/endpoint/input/__init__.py
bbdata/endpoint/input/measures.py
bbdata/endpoint/output/__init__.py
bbdata/endpoint/output/auth.py
bbdata/endpoint/output/comments.py
bbdata/endpoint/output/info.py
bbdata/endpoint/output/me.py
bbdata/endpoint/output/object_groups.py
bbdata/endpoint/output/objects.py
bbdata/endpoint/output/types.py
bbdata/endpoint/output/units.py
bbdata/endpoint/output/user_groups.py
bbdata/endpoint/output/users.py
bbdata/endpoint/output/values.py
bbdata-0.4.3.dist-info/LICENSE
bbdata-0.4.3.dist-info/METADATA
bbdata-0.4.3.dist-info/WHEEL
bbdata-0.4.3.dist-info/top_level.txt
bbdata-0.4.3.dist-info/RECORD
