Metadata-Version: 2.1
Name: bbdata
Version: 0.4.3
Summary: A Python wrapper around the BBData APIs
Home-page: UNKNOWN
Author: Frédéric Montet
Author-email: frederic.montet@hefr.ch
License: UNKNOWN
Platform: UNKNOWN
Classifier: Programming Language :: Python :: 3
Classifier: License :: OSI Approved :: MIT License
Classifier: Operating System :: OS Independent
Requires-Python: >=3.7
Requires-Dist: pandas (<0.26,>=0.25.3)
Requires-Dist: requests (<3,>=2.22.0)
